gpuery/__init__.py
gpuery/entity.py
gpuery/parse.py
gpuery/query.py
gpuery/select.py
gpuery-0.1.0.dist-info/METADATA
gpuery-0.1.0.dist-info/WHEEL
gpuery-0.1.0.dist-info/RECORD
