Metadata-Version: 2.1
Name: gpuery
Version: 0.1.0
Summary: A simple GPU available querier on isolated node
Home-page: https://github.com/HUGHNew/gpuery
License: BSD
Author: Hugh
Author-email: hugh.lpd@gmail.com
Requires-Python: >=3.6,<4.0
Classifier: License :: Other/Proprietary License
Classifier: Programming Language :: Python :: 3
Classifier: Programming Language :: Python :: 3.6
Classifier: Programming Language :: Python :: 3.7
Classifier: Programming Language :: Python :: 3.8
Classifier: Programming Language :: Python :: 3.9
Classifier: Programming Language :: Python :: 3.10
Classifier: Programming Language :: Python :: 3.11
Classifier: Programming Language :: Python :: 3.12
Classifier: Programming Language :: Python :: 3 :: Only
Classifier: Typing :: Typed
Provides-Extra: nvml
Project-URL: Repository, https://github.com/HUGHNew/gpuery
